{
  "player_build_data": [
    {
      "type": "playerBuildTimingData",
      "msg": {
        "build_event_id": "762415f9ced8c4f99b18f7199635a4a7",
        "build_player": 7297,
        "preprocess_player": 54,
        "produce_player_script_assemblies": 2914,
        "build_scripts_dlls": 303,
        "writing_asset_files": 104,
        "postprocess_built_player": 2897,
        "node_summary_table": [
          {
            "name": "Csc",
            "duration": 2044
          }
        ]
      },
      "version": 1
    }
  ]
}